<manifest alg="2" build="30" opt="true" iceEnabled="true" exportTarget="other" resolutions="1x" timestamp="1407119941166">
  <folder name="css">
    <file name="site_global.css" crc="475048684"/>
    <file name="index.css" crc="323808199" ref="index"/>
  </folder>
  <folder name="scripts">
    <file name="jquery-1.8.3.min.js" crc="4245411419" ref="index"/>
    <file name="museutils.js" crc="353204447" ref="index"/>
    <file name="jquery.scrolleffects.js" crc="4083300337" ref="index"/>
    <file name="jquery.watch.js" crc="3923049248" ref="index"/>
    <file name="pie.js" crc="3827607177" ref="index"/>
    <file name="webpro.js" crc="317917375" ref="index"/>
    <file name="musewpslideshow.js" crc="177288662" ref="index"/>
    <file name="jquery.museoverlay.js" crc="524248676" ref="index"/>
    <file name="touchswipe.js" crc="367691663" ref="index"/>
  </folder>
  <folder name="images">
    <file name="u100-4.png" crc="196717169" ref="index"/>
    <file name="u102-4.png" crc="3913161920" ref="index"/>
    <file name="u104-4.png" crc="3798969932" ref="index"/>
    <file name="u75-5.png" crc="59246641" ref="index"/>
    <file name="blank.gif" crc="4208392903" ref="index"/>
    <file name="img_1252.jpg" crc="4278582174" ref="index"/>
    <file name="img_3556-crop-u254.jpg" crc="4183771977" ref="index"/>
    <file name="img_4018.jpg" crc="3953861654" ref="index"/>
    <file name="img_6513.jpg" crc="3873652741" ref="index"/>
    <file name="img_7297.jpg" crc="39179259" ref="index"/>
    <file name="img_9682.jpg" crc="152845017" ref="index"/>
    <file name="img_9870.jpg" crc="3836023713" ref="index"/>
    <file name="img_8542.jpg" crc="235530703" ref="index"/>
    <file name="img_9867.jpg" crc="3817507466" ref="index"/>
    <file name="img_255660x51.jpg" crc="4073624009" ref="index"/>
    <file name="img_125260x46.jpg" crc="27243935" ref="index"/>
    <file name="img_3556-crop-u257.jpg" crc="69902429" ref="index"/>
    <file name="img_401860x55.jpg" crc="4229976102" ref="index"/>
    <file name="img_651360x55.jpg" crc="3959184441" ref="index"/>
    <file name="img_7297-crop-u302.jpg" crc="509649839" ref="index"/>
    <file name="img_968260x55.jpg" crc="4055417114" ref="index"/>
    <file name="img_987066x45.jpg" crc="3783706099" ref="index"/>
    <file name="img_854260x57.jpg" crc="425027561" ref="index"/>
    <file name="img_986760x53.jpg" crc="3803296483" ref="index"/>
    <file name="u170-4.png" crc="304204957" ref="index"/>
    <file name="u251-4.png" crc="484552544" ref="index"/>
    <file name="u260-4.png" crc="3761094673" ref="index"/>
    <file name="u269-4.png" crc="4285962920" ref="index"/>
    <file name="u296-5.png" crc="298854584" ref="index"/>
    <file name="u305-4.png" crc="366445618" ref="index"/>
    <file name="u323-4.png" crc="25776064" ref="index"/>
    <file name="u332-4.png" crc="140493483" ref="index"/>
    <file name="u391-4.png" crc="150128998" ref="index"/>
    <file name="u400-4.png" crc="4068491935" ref="index"/>
    <file name="loading.gif" crc="3815509949" ref="index"/>
    <file name="img_2556.jpg" crc="4018206159" ref="index"/>
    <file name="u776-4.png" crc="196717169" ref="index"/>
    <file name="u778-4.png" crc="3913161920" ref="index"/>
    <file name="u780-4.png" crc="3798969932" ref="index"/>
    <file name="u782-sprite.png" crc="185398833" ref="index"/>
    <file name="u783-4.png" crc="4204597197" ref="index"/>
    <file name="u1149-sprite.png" crc="4186112149" ref="index"/>
    <file name="u1064-4.png" crc="4287115325" ref="index"/>
    <file name="u876-15.png" crc="4203218568" ref="index"/>
    <file name="u934-4.png" crc="3858999210" ref="index"/>
    <file name="u937-4.png" crc="233293625" ref="index"/>
    <file name="u940-4.png" crc="3846340235" ref="index"/>
    <file name="u920-4.png" crc="4134265993" ref="index"/>
    <file name="u921-4.png" crc="439606861" ref="index"/>
    <file name="u922-4.png" crc="370760827" ref="index"/>
    <file name="img_2556427x357.jpg" crc="4262716787" ref="index"/>
    <file name="u1229-10.png" crc="4284360505" ref="index"/>
    <file name="u952-4.png" crc="3858999210" ref="index"/>
    <file name="u963-4.png" crc="233293625" ref="index"/>
    <file name="u962-4.png" crc="3846340235" ref="index"/>
    <file name="u957-4.png" crc="527972766" ref="index"/>
    <file name="u958-4.png" crc="239081774" ref="index"/>
    <file name="u960-4.png" crc="226682888" ref="index"/>
    <file name="img_4018392x358.jpg" crc="53994996" ref="index"/>
    <file name="u1230-10.png" crc="175411563" ref="index"/>
    <file name="u1011-4.png" crc="3858999210" ref="index"/>
    <file name="u1015-4.png" crc="233293625" ref="index"/>
    <file name="u1013-4.png" crc="3846340235" ref="index"/>
    <file name="u1009-4.png" crc="527972766" ref="index"/>
    <file name="u1005-4.png" crc="239081774" ref="index"/>
    <file name="u1006-4.png" crc="226682888" ref="index"/>
    <file name="img_3556356x357.jpg" crc="385849799" ref="index"/>
    <file name="u1231-8.png" crc="276299893" ref="index"/>
    <file name="u1057-4.png" crc="3790374182" ref="index"/>
    <file name="u1053-4.png" crc="133488532" ref="index"/>
    <file name="img_7297350x358.jpg" crc="4155254243" ref="index"/>
    <file name="u1233-16.png" crc="4013997881" ref="index"/>
    <file name="u1083-4.png" crc="3858999210" ref="index"/>
    <file name="u1073-4.png" crc="233293625" ref="index"/>
    <file name="u1074-4.png" crc="3846340235" ref="index"/>
    <file name="u1079-4.png" crc="527972766" ref="index"/>
    <file name="u1081-4.png" crc="239081774" ref="index"/>
    <file name="u1078-4.png" crc="226682888" ref="index"/>
    <file name="img_8542379x355.jpg" crc="41367239" ref="index"/>
    <file name="u1234-12.png" crc="4094413855" ref="index"/>
    <file name="u1091-4.png" crc="3790374182" ref="index"/>
    <file name="u1101-4.png" crc="133488532" ref="index"/>
    <file name="img_9867416x362.jpg" crc="208644221" ref="index"/>
    <file name="u1235-9.png" crc="15686900" ref="index"/>
    <file name="u1111-4.png" crc="3858999210" ref="index"/>
    <file name="u1112-4.png" crc="233293625" ref="index"/>
    <file name="u1122-4.png" crc="3846340235" ref="index"/>
    <file name="u1117-4.png" crc="527972766" ref="index"/>
    <file name="u1115-4.png" crc="239081774" ref="index"/>
    <file name="u1114-4.png" crc="226682888" ref="index"/>
    <file name="img_9682397x360.jpg" crc="3947434671" ref="index"/>
    <file name="u1236-14.png" crc="269766066" ref="index"/>
    <file name="u1140-4.png" crc="3858999210" ref="index"/>
    <file name="u1127-4.png" crc="233293625" ref="index"/>
    <file name="u1136-4.png" crc="3846340235" ref="index"/>
    <file name="u1134-4.png" crc="527972766" ref="index"/>
    <file name="u1133-4.png" crc="239081774" ref="index"/>
    <file name="u1135-4.png" crc="226682888" ref="index"/>
    <file name="img_3274.jpg" crc="301999284" ref="index"/>
    <file name="u859.png" crc="3891866327" ref="index"/>
    <file name="u859-r.png" crc="4282220593" ref="index"/>
    <file name="u859-a.png" crc="3891866327" ref="index"/>
    <file name="u943.png" crc="119804140" ref="index"/>
    <file name="u943-a.png" crc="119804140" ref="index"/>
    <file name="u987-4.png" crc="283782166" ref="index"/>
    <file name="u1048-4.png" crc="4142143072" ref="index"/>
    <file name="u1069-4.png" crc="239596705" ref="index"/>
    <file name="u1088-4.png" crc="225929433" ref="index"/>
    <file name="u1107-4.png" crc="4136311719" ref="index"/>
    <file name="u1141-4.png" crc="232482343" ref="index"/>
    <file name="u1228-4.png" crc="3840379421" ref="index"/>
    <file name="u1183-4.png" crc="4040392468" ref="index"/>
    <file name="pasted image 643x166.jpg" crc="4086561152" ref="index"/>
    <file name="u1243-4.png" crc="239081774" ref="index"/>
    <file name="u1271-4.png" crc="3807830331" ref="index"/>
    <file name="u1254-4.png" crc="4017718258" ref="index"/>
    <file name="u1259-4.png" crc="265258238" ref="index"/>
    <file name="img_6202.jpg" crc="3924189050" ref="index"/>
    <file name="u1284-4.png" crc="103390862" ref="index"/>
    <file name="u1282-4.png" crc="3945372439" ref="index"/>
    <file name="u1281-4.png" crc="4120353041" ref="index"/>
    <file name="u1503-4.png" crc="3858999210" ref="index"/>
    <file name="u1508-4.png" crc="406835588" ref="index"/>
    <file name="u1505-4.png" crc="3846340235" ref="index"/>
    <file name="u1512-4.png" crc="91731031" ref="index"/>
    <file name="u1546-4.png" crc="3858999210" ref="index"/>
    <file name="u1550-4.png" crc="4065064320" ref="index"/>
    <file name="u1547-4.png" crc="3846340235" ref="index"/>
    <file name="u1543-4.png" crc="3762536473" ref="index"/>
    <file name="u1575-4.png" crc="3858999210" ref="index"/>
    <file name="u1570-4.png" crc="3841048759" ref="index"/>
    <file name="u1569-4.png" crc="3846340235" ref="index"/>
    <file name="u1571-4.png" crc="4100690683" ref="index"/>
    <file name="u1594-4.png" crc="203210186" ref="index"/>
    <file name="u1596-4.png" crc="4060402636" ref="index"/>
    <file name="u1618-4.png" crc="246745675" ref="index"/>
    <file name="u1620-4.png" crc="285087312" ref="index"/>
    <file name="u1408.png" crc="4259622501" ref="index"/>
    <file name="u1408-r.png" crc="3857031886" ref="index"/>
    <file name="u1408-a.png" crc="4259622501" ref="index"/>
    <file name="u1552.png" crc="445010967" ref="index"/>
    <file name="u1552-a.png" crc="445010967" ref="index"/>
    <file name="u1566.png" crc="4217295140" ref="index"/>
    <file name="u1566-a.png" crc="4217295140" ref="index"/>
    <file name="u1590-6.png" crc="374237572" ref="index"/>
    <file name="u1614.png" crc="3886771035" ref="index"/>
    <file name="u1614-a.png" crc="3886771035" ref="index"/>
    <file name="u1621.png" crc="4245355725" ref="index"/>
    <file name="u1621-r.png" crc="3988922776" ref="index"/>
    <file name="u1653-4.png" crc="4158523105" ref="index"/>
    <file name="u1655-4.png" crc="185462137" ref="index"/>
    <file name="u1649-6.png" crc="535693029" ref="index"/>
    <file name="u1640.png" crc="123656877" ref="index"/>
    <file name="u1640-r.png" crc="286598743" ref="index"/>
    <file name="u1640-a.png" crc="123656877" ref="index"/>
    <file name="u1642.png" crc="3873121270" ref="index"/>
    <file name="u1642-r.png" crc="498571052" ref="index"/>
    <file name="u1642-a.png" crc="3873121270" ref="index"/>
    <file name="u1644.png" crc="45282405" ref="index"/>
    <file name="u1644-r.png" crc="117756498" ref="index"/>
    <file name="u1644-a.png" crc="45282405" ref="index"/>
    <file name="u1632-4.png" crc="213289383" ref="index"/>
    <file name="img_2840.jpg" crc="432068685" ref="index"/>
    <file name="u1709-6.png" crc="203361782" ref="index"/>
    <file name="u1711-4.png" crc="58817137" ref="index"/>
    <file name="u1679-4.png" crc="3858999210" ref="index"/>
    <file name="u1683-4.png" crc="233293625" ref="index"/>
    <file name="u1682-4.png" crc="3846340235" ref="index"/>
    <file name="u1687-4.png" crc="3777420219" ref="index"/>
    <file name="u1688-4.png" crc="527972766" ref="index"/>
    <file name="u1689-4.png" crc="4129574090" ref="index"/>
    <file name="u1707-4.png" crc="3858999210" ref="index"/>
    <file name="u1702-4.png" crc="233293625" ref="index"/>
    <file name="u1704-4.png" crc="3846340235" ref="index"/>
    <file name="u1695-4.png" crc="457009403" ref="index"/>
    <file name="u1699-4.png" crc="195584935" ref="index"/>
    <file name="u1700-4.png" crc="54845177" ref="index"/>
    <file name="img_5577-crop-u1712.jpg" crc="68258824" ref="index"/>
    <file name="u1721-8.png" crc="503367229" ref="index"/>
    <file name="u1727-4.png" crc="3790374182" ref="index"/>
    <file name="u1726-4.png" crc="133488532" ref="index"/>
    <file name="u1270.png" crc="271496080" ref="index"/>
    <file name="u1270-a.png" crc="271496080" ref="index"/>
    <file name="u1692-4.png" crc="380310058" ref="index"/>
    <file name="u1718-4.png" crc="4066396573" ref="index"/>
  </folder>
  <file name="index.html" crc="342032613" mt="1407119933949" redirect="true"/>
</manifest>